nano_manus/__init__.py
nano_manus/env.py
nano_manus/py.typed
nano_manus/mcp_tool/__init__.py
nano_manus/mcp_tool/official.py
nano_manus/mcp_tool/pool.py
nano_manus/mcp_tool/type.py
nano_manus/planner/__init__.py
nano_manus/planner/parser.py
nano_manus/planner/planner.py
nano_manus/planner/prompts.py
nano_manus/worker/__init__.py
nano_manus/worker/mcp_agent.py
nano_manus/worker/no_tool_agent.py
nano_manus/worker/search_agent.py
nano_manus/worker/terminal_agent.py
nano_manus/worker/type.py
nano_manus-0.0.3.dist-info/METADATA
nano_manus-0.0.3.dist-info/WHEEL
nano_manus-0.0.3.dist-info/RECORD
