Metadata-Version: 2.4
Name: nano_manus
Version: 0.0.3
Summary: Implementing some features of Manus with MCP
Author-email: Gus <contact@memobase.io>
Requires-Python: >=3.11
Requires-Dist: mcp>=1.3.0
Requires-Dist: openai>=1.65.4
Requires-Dist: python-dotenv>=1.0.1
Requires-Dist: rich>=13.9.4
